advancedlib/__init__.py
advancedlib/all.py
advancedlib/antigravity.py
advancedlib/errors.py
advancedlib/importlib.py
advancedlib/itertools.py
advancedlib/math.py
advancedlib/os.py
advancedlib/pdb.py
advancedlib/time.py
advancedlib/tkinter.py
advancedlib/turtle.py
advancedlib/types.py
advancedlib/operator/__init__.py
advancedlib/operator/comparison.py
advancedlib/operator/matical.py
advancedlib/operator/sequence.py
modulelib/__init__.py
modulelib/all_module.py
pyplus/__init__.py
pyplus/__main__.py
pyplus/core.py
pyplus/advancedlib/__init__.py
pyplus/advancedlib/all.py
pyplus/advancedlib/antigravity.py
pyplus/advancedlib/errors.py
pyplus/advancedlib/importlib.py
pyplus/advancedlib/itertools.py
pyplus/advancedlib/math.py
pyplus/advancedlib/os.py
pyplus/advancedlib/pdb.py
pyplus/advancedlib/time.py
pyplus/advancedlib/tkinter.py
pyplus/advancedlib/turtle.py
pyplus/advancedlib/types.py
pyplus/advancedlib/operator/__init__.py
pyplus/advancedlib/operator/comparison.py
pyplus/advancedlib/operator/matical.py
pyplus/advancedlib/operator/sequence.py
pyplus/data/config/alias.toml
pyplus/data/config/config_help.toml
pyplus/data/config/deprecated.toml
pyplus/data/config/doc_help.toml
pyplus/data/config/module_config.toml
pyplus/data/config/update.toml
pyplus/data/docs/markdown/en/README.md
pyplus/data/docs/markdown/en/advancedlib.md
pyplus/data/docs/markdown/en/colors.md
pyplus/data/docs/markdown/en/database_convert.md
pyplus/data/docs/markdown/en/dec.md
pyplus/data/docs/markdown/en/feature.md
pyplus/data/docs/markdown/en/formula.md
pyplus/data/docs/markdown/en/modulelib.md
pyplus/data/docs/markdown/en/password.md
pyplus/data/docs/markdown/en/permission.md
pyplus/data/docs/markdown/en/pycppio.md
pyplus/data/docs/markdown/en/science.md
pyplus/data/docs/markdown/en/stack.md
pyplus/data/docs/markdown/en/tag.md
pyplus/data/docs/markdown/en/tools.md
pyplus/data/docs/markdown/en/update.md
pyplus/data/docs/markdown/en/variables.md
pyplus/data/docs/markdown/en/web.md
python_plus_tools-2.1.3.dist-info/licenses/LICENSE
python_plus_tools-2.1.3.dist-info/METADATA
python_plus_tools-2.1.3.dist-info/WHEEL
python_plus_tools-2.1.3.dist-info/entry_points.txt
python_plus_tools-2.1.3.dist-info/top_level.txt
python_plus_tools-2.1.3.dist-info/RECORD
