Metadata-Version: 2.4
Name: python-plus-tools
Version: 2.1.3
Summary: For the expansion of python content, it covers science, debugging and other fields.
Home-page: https://github.com/xystudio889/pyplus
Author: xystudio
Author-email: xystudio <173288240@qq.com>
License: MIT License
Keywords: debug,science,pyplus,tools,python
Classifier: Programming Language :: Python :: 3
Classifier: License :: OSI Approved :: MIT License
Classifier: Operating System :: OS Independent
Requires-Python: >=3.8
License-File: LICENSE
Requires-Dist: toml>=0.10
Requires-Dist: indently-decorators==1.0
Requires-Dist: cryptography>=3.4
Requires-Dist: imgfit>=0.3
Requires-Dist: colorama>=0.1
Requires-Dist: deprecated>=1
Requires-Dist: typing-extensions>=4.10.0
Requires-Dist: numpy>=1.14
Requires-Dist: matplotlib>=3.4
Requires-Dist: torch>=2
Requires-Dist: pandas>=2
Requires-Dist: requests>=2.27
Requires-Dist: sympy>=1.8
Requires-Dist: markdown>=3.3.6
Requires-Dist: numba>=0.55
Requires-Dist: tomlconfigurer>=0.2
Requires-Dist: documenter>=0.1
Requires-Dist: backupworkspace==0.2.1
Requires-Dist: python-dotenv>=0.19
Provides-Extra: dev
Requires-Dist: sqlmodel>=0.0.4; extra == "dev"
Provides-Extra: test
Requires-Dist: flake8; extra == "test"
Requires-Dist: mypy; extra == "test"
Provides-Extra: build
Requires-Dist: build; extra == "build"
Requires-Dist: setuptools; extra == "build"
Requires-Dist: twine; extra == "build"
Provides-Extra: virtualenv
Requires-Dist: uv; extra == "virtualenv"
Requires-Dist: pipenv; extra == "virtualenv"
Requires-Dist: virtualenv; extra == "virtualenv"
Provides-Extra: studio
Requires-Dist: AI-APIChat; extra == "studio"
Requires-Dist: auto-upgrade-pip; extra == "studio"
Requires-Dist: linecode; extra == "studio"
Requires-Dist: imgfit; extra == "studio"
Requires-Dist: ACE-calc; extra == "studio"
Provides-Extra: web
Requires-Dist: django; extra == "web"
Provides-Extra: other
Requires-Dist: pygame; extra == "other"
Requires-Dist: jupyterlab; extra == "other"
Dynamic: author
Dynamic: home-page
Dynamic: license-file
Dynamic: requires-python
